LICENSE
MANIFEST.in
README.rst
pyproject.toml
requirements.txt
setup.py
discord/__init__.py
discord/__main__.py
discord/abc.py
discord/activity.py
discord/affinity.py
discord/application.py
discord/asset.py
discord/audit_logs.py
discord/automod.py
discord/backoff.py
discord/billing.py
discord/calls.py
discord/channel.py
discord/client.py
discord/colour.py
discord/commands.py
discord/components.py
discord/connections.py
discord/context_managers.py
discord/directory.py
discord/embeds.py
discord/emoji.py
discord/entitlements.py
discord/enums.py
discord/errors.py
discord/experiment.py
discord/file.py
discord/flags.py
discord/gateway.py
discord/guild.py
discord/guild_premium.py
discord/http.py
discord/integrations.py
discord/interactions.py
discord/invite.py
discord/library.py
discord/member.py
discord/mentions.py
discord/message.py
discord/metadata.py
discord/mixins.py
discord/modal.py
discord/oauth2.py
discord/object.py
discord/oggparse.py
discord/opus.py
discord/partial_emoji.py
discord/payments.py
discord/permissions.py
discord/player.py
discord/profile.py
discord/promotions.py
discord/py.typed
discord/raw_models.py
discord/reaction.py
discord/read_state.py
discord/relationship.py
discord/role.py
discord/scheduled_event.py
discord/settings.py
discord/stage_instance.py
discord/state.py
discord/sticker.py
discord/store.py
discord/subscriptions.py
discord/team.py
discord/template.py
discord/threads.py
discord/tracking.py
discord/tutorial.py
discord/user.py
discord/utils.py
discord/voice_client.py
discord/welcome_screen.py
discord/widget.py
discord/bin/libopus-0.x64.dll
discord/bin/libopus-0.x86.dll
discord/ext/commands/__init__.py
discord/ext/commands/_types.py
discord/ext/commands/bot.py
discord/ext/commands/cog.py
discord/ext/commands/context.py
discord/ext/commands/converter.py
discord/ext/commands/cooldowns.py
discord/ext/commands/core.py
discord/ext/commands/errors.py
discord/ext/commands/flags.py
discord/ext/commands/help.py
discord/ext/commands/parameters.py
pycord_self.egg-info/PKG-INFO
pycord_self.egg-info/SOURCES.txt
pycord_self.egg-info/dependency_links.txt
pycord_self.egg-info/requires.txt
pycord_self.egg-info/top_level.txt
